mincepy_sci/__init__.py
mincepy_sci/ase_types.py
mincepy_sci/e3nn_types.py
mincepy_sci/flax_types.py
mincepy_sci/jax_types.py
mincepy_sci/numpy_types.py
mincepy_sci/pandas_types.py
mincepy_sci/plams_types.py
mincepy_sci/provides.py
mincepy_sci/pyilt2_types.py
mincepy_sci/pymatgen_types.py
mincepy_sci/pytorch_types.py
mincepy_sci/rdkit_types.py
mincepy_sci-0.2.0.dist-info/entry_points.txt
mincepy_sci-0.2.0.dist-info/licenses/LICENSE.txt
mincepy_sci-0.2.0.dist-info/WHEEL
mincepy_sci-0.2.0.dist-info/METADATA
mincepy_sci-0.2.0.dist-info/RECORD
