Metadata-Version: 2.4
Name: mincepy-sci
Version: 0.2.0
Summary: Plugins to enable common scientific and machine learning type to be saved by mincePy
Keywords: concurrent,database,nosql,object-store,optimistic-locking,orm,schemaless
Author-email: Martin Uhrin <martin.uhrin.10@ucl.ac.uk>
Requires-Python: >=3.9
Classifier: License :: OSI Approved :: GNU Lesser General Public License v3 or later (LGPLv3+)
Classifier: Programming Language :: Python
Classifier: Programming Language :: Python :: 3.9
Classifier: Programming Language :: Python :: 3.10
Classifier: Programming Language :: Python :: 3.11
Classifier: Programming Language :: Python :: 3.12
Classifier: Programming Language :: Python :: 3.13
License-File: LICENSE.txt
Requires-Dist: bidict
Requires-Dist: mincepy>=0.18.0, <0.19
Requires-Dist: pip ; extra == "dev"
Requires-Dist: pre-commit ; extra == "dev"
Requires-Dist: prospector ; extra == "dev"
Requires-Dist: pylint ; extra == "dev"
Requires-Dist: pytest-cov ; extra == "dev"
Requires-Dist: pytest>4 ; extra == "dev"
Requires-Dist: twine ; extra == "dev"
Requires-Dist: yapf ; extra == "dev"
Requires-Dist: ase ; extra == "full"
Requires-Dist: e3nn ; extra == "full"
Requires-Dist: flax ; extra == "full"
Requires-Dist: jax ; extra == "full"
Requires-Dist: numpy ; extra == "full"
Requires-Dist: pandas ; extra == "full"
Requires-Dist: plams ; extra == "full"
Requires-Dist: pyilt22 ; extra == "full"
Requires-Dist: pymatgen ; extra == "full"
Requires-Dist: rdkit ; extra == "full"
Requires-Dist: torch ; extra == "full"
Project-URL: Homepage, https://github.com/muhrin/mincepy_sci.git
Provides-Extra: dev
Provides-Extra: full
